databricks_ml_bundle/__init__.py
databricks_ml_bundle/cli.py
databricks_ml_bundle/generator.py
databricks_ml_bundle/templates/.gitignore.j2
databricks_ml_bundle/templates/README.md.j2
databricks_ml_bundle/templates/databricks.yaml.j2
databricks_ml_bundle/templates/policies/email_notifications.json.j2
databricks_ml_bundle/templates/policies/mlflow_policy.json.j2
databricks_ml_bundle/templates/requirements-lock.txt.j2
databricks_ml_bundle/templates/requirements.txt.j2
databricks_ml_bundle/templates/src/ds/__init__.py.j2
databricks_ml_bundle/templates/src/ds/deploy_serving.py.j2
databricks_ml_bundle/templates/src/ds/preprocess.py.j2
databricks_ml_bundle/templates/src/ds/register.py.j2
databricks_ml_bundle/templates/src/ds/train.py.j2
databricks_ml_bundle/templates/src/ds/utils/__init__.py.j2
databricks_ml_bundle/templates/src/ds/utils/io.py.j2
databricks_ml_bundle/templates/src/ds/utils/mlflow_utils.py.j2
databricks_ml_bundle-0.1.3.dist-info/METADATA
databricks_ml_bundle-0.1.3.dist-info/WHEEL
databricks_ml_bundle-0.1.3.dist-info/entry_points.txt
databricks_ml_bundle-0.1.3.dist-info/RECORD
