Metadata-Version: 2.3
Name: databricks-ml-bundle
Version: 0.1.3
Summary: CLI tool to generate Databricks ML platform project structure with governance and best practices
Keywords: databricks,mlops,ml-platform,template,cli
Author: Ayush Singh Rawat
Author-email: ayushreawat4583@gmail.com
Requires-Python: >=3.8.1,<4.0.0
Classifier: Development Status :: 4 - Beta
Classifier: Intended Audience :: Developers
Classifier: License :: OSI Approved :: MIT License
Classifier: Programming Language :: Python :: 3
Classifier: Programming Language :: Python :: 3.9
Classifier: Programming Language :: Python :: 3.10
Classifier: Programming Language :: Python :: 3.11
Classifier: Programming Language :: Python :: 3.12
Classifier: Programming Language :: Python :: 3.13
Classifier: Programming Language :: Python :: 3.8
Classifier: Topic :: Scientific/Engineering :: Artificial Intelligence
Classifier: Topic :: Software Development :: Code Generators
Requires-Dist: click (>=8.0.0,<9.0.0)
Requires-Dist: jinja2 (>=3.0.0,<4.0.0)
Requires-Dist: pyyaml (>=6.0,<7.0)
Project-URL: Documentation, https://github.com/AyushSinghRawat-hub/databricks-ml-bundle-cli
Project-URL: Homepage, https://github.com/AyushSinghRawat-hub/databricks-ml-bundle-cli
Project-URL: Repository, https://github.com/AyushSinghRawat-hub/databricks-ml-bundle-cli
